[
  {
    "employeeID": "5a146fe0-d0f0-11ec-ae64-4bba1e1a4805",
    "timeID": "2022-05-01T01:00:00.000Z",
    "createdAt": "2022-05-30T10:50:03.315Z",
    "GSI1SK": "5a146fe0-d0f0-11ec-ae64-4bba1e1a4805",
    "lat": "65.90833",
    "locationType": "OFFICE",
    "long": "180.84012",
    "scanAt": "2022-05-01T01:00:00.000Z",
    "scanReason": "SCAN_IN",
    "scanType": "FINGER_PRINT",
    "Type": "TimeAttendance",
    "__typename": "TimeAttendance"
   },
   {
    "employeeID": "5a146fe0-d0f0-11ec-ae64-4bba1e1a4805",
    "timeID": "2022-05-01T08:00:00.000Z",
    "createdAt": "2022-05-30T10:50:10.627Z",
    "GSI1SK": "5a146fe0-d0f0-11ec-ae64-4bba1e1a4805",
    "lat": "65.90833",
    "locationType": "OFFICE",
    "long": "180.84012",
    "scanAt": "2022-05-01T08:00:00.000Z",
    "scanReason": "SCAN_OUT",
    "scanType": "FINGER_PRINT",
    "Type": "TimeAttendance",
    "__typename": "TimeAttendance"
   },
   {
    "employeeID": "5a146fe0-d0f0-11ec-ae64-4bba1e1a4805",
    "timeID": "2022-05-02T01:00:00.000Z",
    "createdAt": "2022-05-30T10:50:59.136Z",
    "GSI1SK": "5a146fe0-d0f0-11ec-ae64-4bba1e1a4805",
    "lat": "65.90833",
    "locationType": "OFFICE",
    "long": "180.84012",
    "scanAt": "2022-05-02T01:00:00.000Z",
    "scanReason": "SCAN_IN",
    "scanType": "FINGER_PRINT",
    "Type": "TimeAttendance",
    "__typename": "TimeAttendance"
   },
   {
    "employeeID": "5a146fe0-d0f0-11ec-ae64-4bba1e1a4805",
    "timeID": "2022-05-02T01:03:00.000Z",
    "createdAt": "2022-05-30T10:51:09.546Z",
    "GSI1SK": "5a146fe0-d0f0-11ec-ae64-4bba1e1a4805",
    "lat": "65.90833",
    "locationType": "OFFICE",
    "long": "180.84012",
    "scanAt": "2022-05-02T01:03:00.000Z",
    "scanReason": "SCAN_IN",
    "scanType": "FINGER_PRINT",
    "Type": "TimeAttendance",
    "__typename": "TimeAttendance"
   },
   {
    "employeeID": "5a146fe0-d0f0-11ec-ae64-4bba1e1a4805",
    "timeID": "2022-05-02T08:00:00.000Z",
    "createdAt": "2022-05-30T10:51:20.779Z",
    "GSI1SK": "5a146fe0-d0f0-11ec-ae64-4bba1e1a4805",
    "lat": "65.90833",
    "locationType": "OFFICE",
    "long": "180.84012",
    "scanAt": "2022-05-02T08:00:00.000Z",
    "scanReason": "SCAN_OUT",
    "scanType": "FINGER_PRINT",
    "Type": "TimeAttendance",
    "__typename": "TimeAttendance"
   },
   {
    "employeeID": "5a146fe0-d0f0-11ec-ae64-4bba1e1a4805",
    "timeID": "2022-05-03T01:00:00.000Z",
    "createdAt": "2022-05-30T10:54:40.231Z",
    "GSI1SK": "5a146fe0-d0f0-11ec-ae64-4bba1e1a4805",
    "lat": "65.90833",
    "locationType": "OFFICE",
    "long": "180.84012",
    "scanAt": "2022-05-03T01:00:00.000Z",
    "scanReason": "SCAN_IN",
    "scanType": "FINGER_PRINT",
    "Type": "TimeAttendance",
    "__typename": "TimeAttendance"
   },
   {
    "employeeID": "5a146fe0-d0f0-11ec-ae64-4bba1e1a4805",
    "timeID": "2022-05-03T08:00:00.000Z",
    "createdAt": "2022-05-30T10:54:52.793Z",
    "GSI1SK": "5a146fe0-d0f0-11ec-ae64-4bba1e1a4805",
    "lat": "65.90833",
    "locationType": "OFFICE",
    "long": "180.84012",
    "scanAt": "2022-05-03T08:00:00.000Z",
    "scanReason": "SCAN_OUT",
    "scanType": "FINGER_PRINT",
    "Type": "TimeAttendance",
    "__typename": "TimeAttendance"
   }
]
